pulumi_extra/__init__.py
pulumi_extra/errors.py
pulumi_extra/output.py
pulumi_extra/py.typed
pulumi_extra/resource_.py
pulumi_extra/stack_reference.py
pulumi_extra/contrib/__init__.py
pulumi_extra/contrib/aws/__init__.py
pulumi_extra/contrib/aws/autotag.py
pulumi_extra/contrib/aws/common.py
pulumi_extra/contrib/aws/policies/__init__.py
pulumi_extra/contrib/aws/policies/require_description.py
pulumi_extra/contrib/aws/policies/require_tags.py
pulumi_extra/contrib/gcp/__init__.py
pulumi_extra/contrib/gcp/autolabel.py
pulumi_extra/contrib/gcp/common.py
pulumi_extra/contrib/gcp/policies/__init__.py
pulumi_extra/contrib/gcp/policies/require_description.py
pulumi_extra/contrib/gcp/policies/require_labels.py
pulumi_extra/transforms/__init__.py
pulumi_extra/transforms/invoke.py
pulumi_extra/transforms/resource_.py
pulumi_extra/transforms/runtime.py
pulumi_extra-0.1.5.dist-info/METADATA
pulumi_extra-0.1.5.dist-info/WHEEL
pulumi_extra-0.1.5.dist-info/licenses/LICENSE
pulumi_extra-0.1.5.dist-info/RECORD
