Metadata-Version: 2.4
Name: pulumi-extra
Version: 0.1.5
Summary: Extra Pulumi utils and resources.
Project-URL: Homepage, https://github.com/lasuillard-s/pulumi-extra
Project-URL: Repository, https://github.com/lasuillard-s/pulumi-extra.git
Project-URL: Issues, https://github.com/lasuillard-s/pulumi-extra/issues
Author-email: Yuchan Lee <lasuillard@gmail.com>
License-Expression: MIT
License-File: LICENSE
Requires-Python: <4.0,>=3.9
Requires-Dist: braceexpand<1,>=0.1.7
Requires-Dist: jinja2<4,>=3
Requires-Dist: pulumi<4,>=3
Provides-Extra: aws
Requires-Dist: pulumi-aws>=6; extra == 'aws'
Provides-Extra: gcp
Requires-Dist: pulumi-gcp>=8; extra == 'gcp'
Provides-Extra: policy
Requires-Dist: pulumi-policy<2,>=1; extra == 'policy'
